nhl_api_client/__init__.py
nhl_api_client/api/__init__.py
nhl_api_client/api/default/__init__.py
nhl_api_client/api/default/get_all_season_details.py
nhl_api_client/api/default/get_schedule_by_date.py
nhl_api_client/api/default/get_score_details_by_date.py
nhl_api_client/api/default/get_season_standings_by_date.py
nhl_api_client/api/default/get_team_season_schedule.py
nhl_api_client/api/default/get_team_week_schedule_by_date.py
nhl_api_client/api/default/get_v1_location.py
nhl_api_client/api/default/get_v1_player_8476453_game_log_20232024_2.py
nhl_api_client/api/default/get_v1_player_8476453_landing.py
nhl_api_client/api/default/get_v1_player_spotlight.py
nhl_api_client/api/default/get_v1_standings_season.py
nhl_api_client/api/game/__init__.py
nhl_api_client/api/game/get_game_play_by_play_by_id.py
nhl_api_client/client.py
nhl_api_client/errors.py
nhl_api_client/models/__init__.py
nhl_api_client/models/game.py
nhl_api_client/models/game_clock.py
nhl_api_client/models/game_game_outcome.py
nhl_api_client/models/game_period_descriptor.py
nhl_api_client/models/get_all_season_details_response_200.py
nhl_api_client/models/get_all_season_details_response_200_data_item.py
nhl_api_client/models/get_v1_location_response_200.py
nhl_api_client/models/get_v1_player_8476453_game_log_202320242_response_200.py
nhl_api_client/models/get_v1_player_8476453_game_log_202320242_response_200_game_log_item.py
nhl_api_client/models/get_v1_player_8476453_game_log_202320242_response_200_player_stats_seasons_item.py
nhl_api_client/models/get_v1_player_8476453_landing_response_200.py
nhl_api_client/models/get_v1_player_8476453_landing_response_200_awards_item.py
nhl_api_client/models/get_v1_player_8476453_landing_response_200_awards_item_seasons_item.py
nhl_api_client/models/get_v1_player_8476453_landing_response_200_career_totals.py
nhl_api_client/models/get_v1_player_8476453_landing_response_200_career_totals_playoffs.py
nhl_api_client-1.0.6.dist-info/METADATA
nhl_api_client-1.0.6.dist-info/WHEEL
nhl_api_client-1.0.6.dist-info/RECORD
